renotize/__init__.py
renotize/renotize.py
renotize-1.6.0.dist-info/entry_points.txt
renotize-1.6.0.dist-info/LICENSE
renotize-1.6.0.dist-info/WHEEL
renotize-1.6.0.dist-info/METADATA
renotize-1.6.0.dist-info/RECORD
