Metadata-Version: 2.1
Name: renotize
Version: 1.6.0
Summary: A utility script for quickly and automatically notarizing Ren'Py applications for macOS.
Home-page: https://github.com/kobaltcore/renotize
License: MIT
Author: CobaltCore
Author-email: cobaltcore@yandex.com
Requires-Python: >=3.7,<4.0
Classifier: License :: OSI Approved :: MIT License
Classifier: Programming Language :: Python :: 3
Classifier: Programming Language :: Python :: 3.10
Classifier: Programming Language :: Python :: 3.7
Classifier: Programming Language :: Python :: 3.8
Classifier: Programming Language :: Python :: 3.9
Requires-Dist: PyYAML (>=6.0,<7.0)
Requires-Dist: arrow (>=1.2.2,<2.0.0)
Requires-Dist: click (>=8.1.3,<9.0.0)
Requires-Dist: rich (>=12.4.1,<13.0.0)
Requires-Dist: tqdm (>=4.64.0,<5.0.0)
Project-URL: Repository, https://github.com/kobaltcore/renotize
